grig/__init__.py
grig/clean_image.py
grig/resample.py
grig/resample_base.py
grig/resample_kernel.py
grig/resample_kernel_utils.py
grig/resample_polynomial.py
grig/resample_utils.py
grig/version.py
grig/grid/__init__.py
grig/grid/base_grid.py
grig/grid/kernel_grid.py
grig/grid/polynomial_grid.py
grig/grid/tests/__init__.py
grig/grid/tests/test_base_grid/__init__.py
grig/grid/tests/test_base_grid/test_methods.py
grig/grid/tests/test_base_grid/test_properties.py
grig/grid/tests/test_kernel_grid/__init__.py
grig/grid/tests/test_kernel_grid/test_methods.py
grig/grid/tests/test_kernel_grid/test_properties.py
grig/grid/tests/test_polynomial_grid/__init__.py
grig/grid/tests/test_polynomial_grid/test_methods.py
grig/grid/tests/test_polynomial_grid/test_properties.py
grig/tests/__init__.py
grig/tests/test_clean_image.py
grig/tests/test_resample_base/__init__.py
grig/tests/test_resample_base/test_check_call_arguments.py
grig/tests/test_resample_base/test_check_order.py
grig/tests/test_resample_base/test_estimate_feature_windows.py
grig/tests/test_resample_base/test_methods.py
grig/tests/test_resample_base/test_process_input_data.py
grig/tests/test_resample_base/test_properties.py
grig/tests/test_resample_base/test_reduction_settings.py
grig/tests/test_resample_kernel/__init__.py
grig/tests/test_resample_kernel/test_expected_results.py
grig/tests/test_resample_kernel/test_methods.py
grig/tests/test_resample_kernel/test_properties.py
grig/tests/test_resample_polynomial/__init__.py
grig/tests/test_resample_polynomial/test_calculate_adaptive_smoothing.py
grig/tests/test_resample_polynomial/test_call.py
grig/tests/test_resample_polynomial/test_expected_results.py
grig/tests/test_resample_polynomial/test_methods.py
grig/tests/test_resample_polynomial/test_parallel.py
grig/tests/test_resample_polynomial/test_properties.py
grig/tests/test_resample_polynomial/test_reduction_settings.py
grig/tests/test_resample_polynomial/test_resamp.py
grig/tests/test_resample_utils/__init__.py
grig-1.0.0.dist-info/LICENSE.rst
grig-1.0.0.dist-info/METADATA
grig-1.0.0.dist-info/WHEEL
grig-1.0.0.dist-info/top_level.txt
grig-1.0.0.dist-info/RECORD
