Metadata-Version: 2.1
Name: grig
Version: 1.0.0
Summary: N-Dimensional Resampler for Irregularly Gridded Data
Author-email: SOFIA-USRA <mclarke@sofia.usra.edu>
License: Copyright 2023 Universities Space Research Association
Project-URL: Homepage, https://github.com/SOFIA-USRA/grig
Classifier: Intended Audience :: Science/Research
Classifier: License :: OSI Approved :: BSD License
Classifier: Operating System :: OS Independent
Classifier: Programming Language :: Python :: 3
Classifier: Programming Language :: Python :: Implementation :: CPython
Classifier: Topic :: Scientific/Engineering :: Astronomy
Classifier: Topic :: Scientific/Engineering :: Physics
Requires-Python: >=3.11
License-File: LICENSE.rst
Requires-Dist: bottleneck >=1.3.7
Requires-Dist: cloudpickle >=2.2.1
Requires-Dist: joblib >=1.3.0
Requires-Dist: numba >=0.57.1
Requires-Dist: numpy >=1.24.4
Requires-Dist: psutil >=5.9.5
Requires-Dist: scikit-learn >=1.3.0
Requires-Dist: scipy >=1.11.1
Provides-Extra: docs
Requires-Dist: graphviz ; extra == 'docs'
Requires-Dist: imageio ; extra == 'docs'
Requires-Dist: matplotlib >=3.7.2 ; extra == 'docs'
Requires-Dist: numpydoc >=1.5.0 ; extra == 'docs'
Requires-Dist: sphinx >=5 ; extra == 'docs'
Requires-Dist: sphinx-rtd-theme ; extra == 'docs'
Requires-Dist: sphinx-automodapi ; extra == 'docs'
Requires-Dist: sphinx-issues ; extra == 'docs'
Requires-Dist: tomli ; extra == 'docs'
Provides-Extra: test
Requires-Dist: pytest >=7.4.0 ; extra == 'test'
Requires-Dist: pytest-cov >=4.1.0 ; extra == 'test'
Requires-Dist: ruff ; extra == 'test'
